setup.cfg
setup.py
pennathletics/__init__.py
pennathletics/athletes.py
pennathletics/models.py
pennathletics/parse.py
pennathletics/scraper.py
pennathletics/sportsdata.py
pennathletics.egg-info/PKG-INFO
pennathletics.egg-info/SOURCES.txt
pennathletics.egg-info/dependency_links.txt
pennathletics.egg-info/requires.txt
pennathletics.egg-info/top_level.txt