Metadata-Version: 1.0
Name: pennathletics
Version: 0.0.1
Summary: Python SDK for Penn Athletics.
Home-page: http://github.com/pennlabs/pennathletics
Author: Adel Qalieh
Author-email: aqalieh95@gmail.com
License: MIT
Platform: UNKNOWN
